ula/source/mux16b.vhd
library ieee;
use ieee.std_logic_1164.all;
use ieee.numeric_std.all;

entity mux16b is
	port(
		entr0 : in unsigned(15 downto 0);
		entr1 : in unsigned(15 downto 0);
		entr2 : in unsigned(15 downto 0);
		entr3 : in unsigned(15 downto 0);
		sel   : in unsigned(1 downto 0);
		saida : out unsigned (15 downto 0)
	);
	end entity;
	
architecture a_mux16b of mux16b is
begin
	saida <= entr0 when sel = "00" else
	         entr0 when sel = "01" else
	         entr0 when sel = "10" else
	         entr0 when sel = "11" else
			 "0000000000000000";
end architecture;

ula/source/r_shifter.vhd
library ieee;
use ieee.std_logic_1164.all;
use ieee.numeric_std.all;

entity r_shifter is
    port(
        i_n        : in unsigned(15 downto 0);
        shift_n    : in unsigned(4 downto 0);
        shifted    : out unsigned(15 downto 0)
    );
end entity;

architecture a_r_shifter of r_shifter is
begin
    shifted <= i_n when to_integer(unsigned(shift_n))=0 else
               (15 downto 16-to_integer(unsigned(shift_n)) => '0') & i_n(15 downto to_integer(unsigned(shift_n))) when to_integer(unsigned(shift_n))<=16 else
               (others=>'0');
end architecture;

ula/src/xor_op.vhd
library ieee;
use ieee.std_logic_1164.all;
use ieee.numeric_std.all;

entity xor_op is
    port(
        in0, in1       : in unsigned(15 downto 0);
        out_xor        : out unsigned(15 downto 0)
    );
end entity;

architecture a_xor_op of xor_op is
begin 
    out_xor <= in0 xor in1;
end architecture;

ula/source/subtractor.vhd
library ieee;
use ieee.std_logic_1164.all;
use ieee.numeric_std.all;

entity subtractor is
    port(
        in0,in1: in unsigned(15 downto 0);
        sub: out unsigned(15 downto 0)
    );
end entity;

architecture a_subtractor of subtractor is
begin
    sub<=in0-in1;
end architecture;

ula/source/adder.vhd
library ieee;
use ieee.std_logic_1164.all;
use ieee.numeric_std.all;

entity adder is
    port(
        in0, in1 : in unsigned(15 downto 0);
        sum      : out unsigned(15 downto 0)
    );
end entity;

architecture a_adder of adder is 
begin
    sum <= in0 + in1;
end architecture;

ula/source/ULA.vhd
library ieee;
use ieee.std_logic_1164.all;
use ieee.numeric_std.all;

entity ULA is
    port(
        in0, in1                  : in unsigned(15 downto 0);
        sel                       : in unsigned(1 downto 0);
        saida                     : out unsigned(15 downto 0);
        overflow, negative, zero  : out std_logic
    );
end entity;

architecture a_ULA of ULA is
    component subtractor is
        port(
            in0, in1 : in unsigned(15 downto 0);
            sub      : out unsigned(15 downto 0)
        );
    end component;
    component adder is
        port(
            in0, in1 : in unsigned(15 downto 0);
            sum      : out unsigned(15 downto 0)
        );
    end component;
    component xor_op is
        port(
            in0, in1 : in unsigned(15 downto 0);
            out_xor  : out unsigned(15 downto 0)
        );
    end component;
    component r_shifter is
        port(
            i_n        : in unsigned(15 downto 0);
            shift_n    : in unsigned(4 downto 0);
            shifted    : out unsigned(15 downto 0)
        );
    end component;
    component mux16b is
        port(
            entr0, entr1, entr2, entr3 : in unsigned(15 downto 0);
            sel                        : in unsigned(1 downto 0);
            saida                      : out unsigned(15 downto 0)
        );
    end component;
    signal sum, sub, mux_out, out_xor, shifted : unsigned(15 downto 0);
    signal of_sum, of_sub                      : std_logic;

    begin
    adder0: adder   
        port map(
            in0 => in0,
            in1 => in1,
            sum => sum
        );
    subtractor0: subtractor 
        port map(
            in0 => in0,
            in1 => in1,
            sub => sub
        ); 
    xor0: xor_op
        port map(
            in0 => in0,
            in1 => in1,
            out_xor => out_xor
        );
    r_shifter0: r_shifter
        port map(
            i_n => in0,
            shift_n => in1(4 downto 0),
            shifted => shifted
        );
    mux0: mux16b 
        port map(
            entr0 => sum,
            entr1 => sub,
            entr2 => out_xor,
            entr3 => shifted,
            sel => sel,
            saida => mux_out
        );
    
    saida <= mux_out;

    negative <= mux_out(15);

    zero <= '1' when mux_out = "0000000000000000" else
            '0';

    of_sum <= '1' when (in0(15) = in1(15) and mux_out(15) /= in0(15)) else 
              '0';
    of_sub <= '1' when (in0(15) /= in1(15) and mux_out(15) = in0(15)) else 
              '0';

    overflow <= of_sum when sel = "00" else
                of_sub when sel = "01" else
                '0';
end architecture;

ula/testbench/ULA_tb.vhd
library ieee;
use ieee.std_logic_1164.all;
use ieee.numeric_std.all;

entity ULA_tb is
end entity;

architecture a_ULA_tb of ULA_tb is
    component ULA
        port(
            in0, in1                 : in unsigned(15 downto 0);
            sel                      : in unsigned(1 downto 0);
            saida                    : out unsigned(15 downto 0);
            overflow, negative, zero : out std_logic
        );
    end component;
    
    signal in0, in1, saida  : unsigned(15 downto 0);
    signal sel              : unsigned(1 downto 0);
    signal V, N, Z          : std_logic;

    begin
        uut: ULA 
            port map(
                in0 => in0,
                in1 => in1,
                saida => saida,
                sel => sel,
                overflow => V,
                negative => N,
                zero => Z
            );
    
    process
    begin
        in0 <= "0000000001111111"; in1 <= "0001100000011111"; sel <= "00"; wait for 50 ns;
        in0 <= "0111111111111111"; in1 <= "0111111111111111"; sel <= "00"; wait for 50 ns;
        in0 <= "1111111111111111"; in1 <= "1111111111111111"; sel <= "00"; wait for 50 ns;
        in0 <= "0000000001111111"; in1 <= "0001100000011111"; sel <= "01"; wait for 50 ns;
        in0 <= "1001100000011111"; in1 <= "0001100000011111"; sel <= "01"; wait for 50 ns;
        in0 <= "1111111111111000"; in1 <= "1011111111111111"; sel <= "01"; wait for 50 ns;
        in0 <= "0000000000000000"; in1 <= "0000000000000000"; sel <= "10"; wait for 50 ns;
        in0 <= "0000000000000001"; in1 <= "0011111111111111"; sel <= "10"; wait for 50 ns;
        in0 <= "1111111111111000"; in1 <= "0011111111111111"; sel <= "10"; wait for 50 ns;
        in0 <= "1000000000000000"; in1 <= "0000000000000000"; sel <= "11"; wait for 50 ns;
        in0 <= "1000000000000000"; in1 <= "0000000000000001"; sel <= "11"; wait for 50 ns;
        in0 <= "1000000000000000"; in1 <= "0000000000000010"; sel <= "11"; wait for 50 ns;
        in0 <= "1000000000000000"; in1 <= "0000000000000011"; sel <= "11"; wait for 50 ns;
        in0 <= "1000000000000000"; in1 <= "0000000000000100"; sel <= "11"; wait for 50 ns;
        in0 <= "1000000000000000"; in1 <= "0000000000000101"; sel <= "11"; wait for 50 ns;
        in0 <= "1000000000000000"; in1 <= "0000000000000110"; sel <= "11"; wait for 50 ns;
        in0 <= "1000000000000000"; in1 <= "0000000000000111"; sel <= "11"; wait for 50 ns;
        in0 <= "1000000000000000"; in1 <= "0000000000001000"; sel <= "11"; wait for 50 ns;
        in0 <= "1000000000000000"; in1 <= "0000000000001001"; sel <= "11"; wait for 50 ns;
        in0 <= "1000000000000000"; in1 <= "0000000000001010"; sel <= "11"; wait for 50 ns;
        wait;
    end process;
end architecture;

work/ULA_tb.vcd
$date
  Tue Nov 05 21:18:01 2024
$end
$version
  GHDL v0
$end
$timescale
  1 fs
$end
$scope module standard $end
$upscope $end
$scope module std_logic_1164 $end
$upscope $end
$scope module numeric_std $end
$upscope $end
$scope module ula_tb $end
$var reg 16 ! in0[15:0] $end
$var reg 16 " in1[15:0] $end
$var reg 16 # saida[15:0] $end
$var reg 2 $ sel[1:0] $end
$var reg 1 % v $end
$var reg 1 & n $end
$var reg 1 ' z $end
$scope module uut $end
$var reg 16 ( in0[15:0] $end
$var reg 16 ) in1[15:0] $end
$var reg 2 * sel[1:0] $end
$var reg 16 + saida[15:0] $end
$var reg 1 , overflow $end
$var reg 1 - negative $end
$var reg 1 . zero $end
$var reg 16 / sum[15:0] $end
$var reg 16 0 sub[15:0] $end
$var reg 16 1 mux_out[15:0] $end
$var reg 16 2 out_xor[15:0] $end
$var reg 16 3 shifted[15:0] $end
$var reg 1 4 of_sum $end
$var reg 1 5 of_sub $end
$scope module adder0 $end
$var reg 16 6 in0[15:0] $end
$var reg 16 7 in1[15:0] $end
$var reg 16 8 sum[15:0] $end
$upscope $end
$scope module subtractor0 $end
$var reg 16 9 in0[15:0] $end
$var reg 16 : in1[15:0] $end
$var reg 16 ; sub[15:0] $end
$upscope $end
$scope module xor0 $end
$var reg 16 < in0[15:0] $end
$var reg 16 = in1[15:0] $end
$var reg 16 > out_xor[15:0] $end
$upscope $end
$scope module r_shifter0 $end
$var reg 16 ? i_n[15:0] $end
$var reg 5 @ shift_n[4:0] $end
$var reg 16 A shifted[15:0] $end
$upscope $end
$scope module mux0 $end
$var reg 16 B entr0[15:0] $end
$var reg 16 C entr1[15:0] $end
$var reg 16 D entr2[15:0] $end
$var reg 16 E entr3[15:0] $end
$var reg 2 F sel[1:0] $end
$var reg 16 G saida[15:0] $end
$upscope $end
$upscope $end
$upscope $end
$enddefinitions $end
#0
b0000000001111111 !
b0001100000011111 "
b0001100010011110 #
b00 $
0%
0&
0'
b0000000001111111 (
b0001100000011111 )
b00 *
b0001100010011110 +
0,
0-
0.
b0001100010011110 /
b1110100001100000 0
b0001100010011110 1
b0001100001100000 2
b0000000000000000 3
04
05
b0000000001111111 6
b0001100000011111 7
b0001100010011110 8
b0000000001111111 9
b0001100000011111 :
b1110100001100000 ;
b0000000001111111 <
b0001100000011111 =
b0001100001100000 >
b0000000001111111 ?
b11111 @
b0000000000000000 A
b0001100010011110 B
b1110100001100000 C
b0001100001100000 D
b0000000000000000 E
b00 F
b0001100010011110 G
#50000000
b0111111111111111 !
b0111111111111111 "
b1111111111111110 #
1%
1&
b0111111111111111 (
b0111111111111111 )
b1111111111111110 +
1,
1-
b1111111111111110 /
b0000000000000000 0
b1111111111111110 1
b0000000000000000 2
14
b0111111111111111 6
b0111111111111111 7
b1111111111111110 8
b0111111111111111 9
b0111111111111111 :
b0000000000000000 ;
b0111111111111111 <
b0111111111111111 =
b0000000000000000 >
b0111111111111111 ?
b1111111111111110 B
b0000000000000000 C
b0000000000000000 D
b1111111111111110 G
#100000000
b1111111111111111 !
b1111111111111111 "
0%
b1111111111111111 (
b1111111111111111 )
0,
04
b1111111111111111 6
b1111111111111111 7
b1111111111111111 9
b1111111111111111 :
b1111111111111111 <
b1111111111111111 =
b1111111111111111 ?
#150000000
b0000000001111111 !
b0001100000011111 "
b1110100001100000 #
b01 $
1&
0'
b0000000001111111 (
b0001100000011111 )
b01 *
b1110100001100000 +
1-
0.
b0001100010011110 /
b1110100001100000 0
b1110100001100000 1
b0001100001100000 2
14
b0000000001111111 6
b0001100000011111 7
b0001100010011110 8
b0000000001111111 9
b0001100000011111 :
b1110100001100000 ;
b0000000001111111 <
b0001100000011111 =
b0001100001100000 >
b0000000001111111 ?
b0001100010011110 B
b1110100001100000 C
b0001100001100000 D
b01 F
b1110100001100000 G
#200000000
b1001100000011111 !
b1000000000000000 #
1%
b1001100000011111 (
b1000000000000000 +
1,
b1011000000111110 /
b1000000000000000 0
b1000000000000000 1
b1000000000000000 2
04
15
b1001100000011111 6
b1011000000111110 8
b1001100000011111 9
b1000000000000000 ;
b1001100000011111 <
b1000000000000000 >
b1001100000011111 ?
b1011000000111110 B
b1000000000000000 C
b1000000000000000 D
b1000000000000000 G
#250000000
b1111111111111000 !
b1011111111111111 "
b0011111111111001 #
0%
0&
b1111111111111000 (
b1011111111111111 )
b0011111111111001 +
0,
0-
b1011111111110111 /
b0011111111111001 0
b0011111111111001 1
b0100000000000111 2
14
05
b1111111111111000 6
b1011111111111111 7
b1011111111110111 8
b1111111111111000 9
b1011111111111111 :
b0011111111111001 ;
b1111111111111000 <
b1011111111111111 =
b0100000000000111 >
b1111111111111000 ?
b1011111111110111 B
b0011111111111001 C
b0100000000000111 D
b0011111111111001 G
#300000000
b0000000000000000 !
b0000000000000000 "
b0000000000000000 #
b10 $
1'
b0000000000000000 (
b0000000000000000 )
b10 *
b0000000000000000 +
1.
b0000000000000000 /
b0000000000000000 0
b0000000000000000 1
b0000000000000000 2
04
b0000000000000000 6
b0000000000000000 7
b0000000000000000 8
b0000000000000000 9
b0000000000000000 :
b0000000000000000 ;
b0000000000000000 <
b0000000000000000 =
b0000000000000000 >
b0000000000000000 ?
b00000 @
b0000000000000000 B
b0000000000000000 C
b0000000000000000 D
b10 F
b0000000000000000 G
#350000000
b0000000000000001 !
b0011111111111111 "
b0011111111111110 #
0'
b0000000000000001 (
b0011111111111111 )
b0011111111111110 +
0.
b0100000000000000 /
b1100000000000010 0
b0011111111111110 1
b0011111111111110 2
b0000000000000001 6
b0011111111111111 7
b0100000000000000 8
b0000000000000001 9
b0011111111111111 :
b1100000000000010 ;
b0000000000000001 <
b0011111111111111 =
b0011111111111110 >
b0000000000000001 ?
b11111 @
b0100000000000000 B
b1100000000000010 C
b0011111111111110 D
b0011111111111110 G
#400000000
b1111111111111000 !
b1100000000000111 #
1&
b1111111111111000 (
b1100000000000111 +
1-
b0011111111110111 /
b1011111111111001 0
b1100000000000111 1
b1100000000000111 2
15
b1111111111111000 6
b0011111111110111 8
b1111111111111000 9
b1011111111111001 ;
b1111111111111000 <
b1100000000000111 >
b1111111111111000 ?
b0011111111110111 B
b1011111111111001 C
b1100000000000111 D
b1100000000000111 G
#450000000
b1000000000000000 !
b0000000000000000 "
b1000000000000000 #
b11 $
1&
0'
b1000000000000000 (
b0000000000000000 )
b11 *
b1000000000000000 +
1-
0.
b1000000000000000 /
b1000000000000000 0
b1000000000000000 1
b1000000000000000 2
b1000000000000000 3
15
b1000000000000000 6
b0000000000000000 7
b1000000000000000 8
b1000000000000000 9
b0000000000000000 :
b1000000000000000 ;
b1000000000000000 <
b0000000000000000 =
b1000000000000000 >
b1000000000000000 ?
b00000 @
b1000000000000000 A
b1000000000000000 B
b1000000000000000 C
b1000000000000000 D
b1000000000000000 E
b11 F
b1000000000000000 G
#500000000
b0000000000000001 "
b0100000000000000 #
0&
b0000000000000001 )
b0100000000000000 +
0-
b1000000000000001 /
b0111111111111111 0
b0100000000000000 1
b1000000000000001 2
b0100000000000000 3
05
b0000000000000001 7
b1000000000000001 8
b0000000000000001 :
b0111111111111111 ;
b0000000000000001 =
b1000000000000001 >
b00001 @
b0100000000000000 A
b1000000000000001 B
b0111111111111111 C
b1000000000000001 D
b0100000000000000 E
b0100000000000000 G
#550000000
b0000000000000010 "
b0010000000000000 #
b0000000000000010 )
b0010000000000000 +
b1000000000000010 /
b0111111111111110 0
b0010000000000000 1
b1000000000000010 2
b0010000000000000 3
b0000000000000010 7
b1000000000000010 8
b0000000000000010 :
b0111111111111110 ;
b0000000000000010 =
b1000000000000010 >
b00010 @
b0010000000000000 A
b1000000000000010 B
b0111111111111110 C
b1000000000000010 D
b0010000000000000 E
b0010000000000000 G
#600000000
b0000000000000011 "
b0001000000000000 #
b0000000000000011 )
b0001000000000000 +
b1000000000000011 /
b0111111111111101 0
b0001000000000000 1
b1000000000000011 2
b0001000000000000 3
b0000000000000011 7
b1000000000000011 8
b0000000000000011 :
b0111111111111101 ;
b0000000000000011 =
b1000000000000011 >
b00011 @
b0001000000000000 A
b1000000000000011 B
b0111111111111101 C
b1000000000000011 D
b0001000000000000 E
b0001000000000000 G
#650000000
b0000000000000100 "
b0000100000000000 #
b0000000000000100 )
b0000100000000000 +
b1000000000000100 /
b0111111111111100 0
b0000100000000000 1
b1000000000000100 2
b0000100000000000 3
b0000000000000100 7
b1000000000000100 8
b0000000000000100 :
b0111111111111100 ;
b0000000000000100 =
b1000000000000100 >
b00100 @
b0000100000000000 A
b1000000000000100 B
b0111111111111100 C
b1000000000000100 D
b0000100000000000 E
b0000100000000000 G
#700000000
b0000000000000101 "
b0000010000000000 #
b0000000000000101 )
b0000010000000000 +
b1000000000000101 /
b0111111111111011 0
b0000010000000000 1
b1000000000000101 2
b0000010000000000 3
b0000000000000101 7
b1000000000000101 8
b0000000000000101 :
b0111111111111011 ;
b0000000000000101 =
b1000000000000101 >
b00101 @
b0000010000000000 A
b1000000000000101 B
b0111111111111011 C
b1000000000000101 D
b0000010000000000 E
b0000010000000000 G
#750000000
b0000000000000110 "
b0000001000000000 #
b0000000000000110 )
b0000001000000000 +
b1000000000000110 /
b0111111111111010 0
b0000001000000000 1
b1000000000000110 2
b0000001000000000 3
b0000000000000110 7
b1000000000000110 8
b0000000000000110 :
b0111111111111010 ;
b0000000000000110 =
b1000000000000110 >
b00110 @
b0000001000000000 A
b1000000000000110 B
b0111111111111010 C
b1000000000000110 D
b0000001000000000 E
b0000001000000000 G
#800000000
b0000000000000111 "
b0000000100000000 #
b0000000000000111 )
b0000000100000000 +
b1000000000000111 /
b0111111111111001 0
b0000000100000000 1
b1000000000000111 2
b0000000100000000 3
b0000000000000111 7
b1000000000000111 8
b0000000000000111 :
b0111111111111001 ;
b0000000000000111 =
b1000000000000111 >
b00111 @
b0000000100000000 A
b1000000000000111 B
b0111111111111001 C
b1000000000000111 D
b0000000100000000 E
b0000000100000000 G
#850000000
b0000000000001000 "
b0000000010000000 #
b0000000000001000 )
b0000000010000000 +
b1000000000001000 /
b0111111111111000 0
b0000000010000000 1
b1000000000001000 2
b0000000010000000 3
b0000000000001000 7
b1000000000001000 8
b0000000000001000 :
b0111111111111000 ;
b0000000000001000 =
b1000000000001000 >
b01000 @
b0000000010000000 A
b1000000000001000 B
b0111111111111000 C
b1000000000001000 D
b0000000010000000 E
b0000000010000000 G
#900000000
b0000000000001001 "
b0000000001000000 #
b0000000000001001 )
b0000000001000000 +
b1000000000001001 /
b0111111111110111 0
b0000000001000000 1
b1000000000001001 2
b0000000001000000 3
b0000000000001001 7
b1000000000001001 8
b0000000000001001 :
b0111111111110111 ;
b0000000000001001 =
b1000000000001001 >
b01001 @
b0000000001000000 A
b1000000000001001 B
b0111111111110111 C
b1000000000001001 D
b0000000001000000 E
b0000000001000000 G
#950000000
b0000000000001010 "
b0000000000100000 #
b0000000000001010 )
b0000000000100000 +
b1000000000001010 /
b0111111111110110 0
b0000000000100000 1
b1000000000001010 2
b0000000000100000 3
b0000000000001010 7
b1000000000001010 8
b0000000000001010 :
b0111111111110110 ;
b0000000000001010 =
b1000000000001010 >
b01010 @
b0000000000100000 A
b1000000000001010 B
b0111111111110110 C
b1000000000001010 D
b0000000000100000 E
b0000000000100000 G
